{"project":"joyent/manta-muskie","branch":"master","id":"If610b0aab574106f921c0e2c40fe0df10790ede5","number":"5115","subject":"MANTA-4030 many images using node 0.10 or 0.12 broken by transitive lru-cache@4.1.4 dep Reviewed by: Alex Wilson \u003calex.wilson@joyent.com\u003e Approved by: Alex Wilson \u003calex.wilson@joyent.com\u003e","owner":{"name":"Trent Mick","email":"trentm@gmail.com","username":"trentm"},"url":"https://cr.joyent.us/5115","commitMessage":"MANTA-4030 many images using node 0.10 or 0.12 broken by transitive lru-cache@4.1.4 dep\nReviewed by: Alex Wilson \u003calex.wilson@joyent.com\u003e\nApproved by: Alex Wilson \u003calex.wilson@joyent.com\u003e\n","createdOn":1542940552,"lastUpdated":1543266475,"open":false,"status":"MERGED","comments":[{"timestamp":1542940552,"reviewer":{"name":"Trent Mick","email":"trentm@gmail.com","username":"trentm"},"message":"Uploaded patch set 1."},{"timestamp":1542940553,"reviewer":{"name":"Trent Mick","email":"trentm@gmail.com","username":"trentm"},"message":"Patch Set 1:\n\nNew commits:\n    \n    commit 0528218ee78ee7524f007655317c34aabf19ab20\n    \n    fix it"},{"timestamp":1542940583,"reviewer":{"name":"Joyent Automation","username":"joyent-automation"},"message":"Patch Set 1: CI-Testing+1\n\n\"make check\" passed ok"},{"timestamp":1543258932,"reviewer":{"name":"Alex Wilson","email":"alex@cooperi.net","username":"arekinath"},"message":"Patch Set 1: Code-Review+1 Integration-Approval+1"},{"timestamp":1543266469,"reviewer":{"name":"Trent Mick","email":"trentm@gmail.com","username":"trentm"},"message":"Uploaded patch set 2: Commit message was updated."},{"timestamp":1543266475,"reviewer":{"name":"Gerrit Code Review","email":"no-reply@cr.joyent.us"},"message":"Change has been successfully merged by Trent Mick"}],"currentPatchSet":{"number":"2","revision":"f610b0aab574106f921c0e2c40fe0df10790ede5","parents":["4d9be47aa0e74267e0211f566c07f6ddad566db6"],"ref":"refs/changes/15/5115/2","uploader":{"name":"Trent Mick","email":"trentm@gmail.com","username":"trentm"},"createdOn":1543266469,"author":{"name":"Trent Mick","email":"trentm@gmail.com","username":"trentm"},"isDraft":false,"kind":"NO_CODE_CHANGE","approvals":[{"type":"CI-Testing","description":"CI-Testing","value":"1","grantedOn":1542940583,"by":{"name":"Joyent Automation","username":"joyent-automation"}},{"type":"Code-Review","description":"Code-Review","value":"1","grantedOn":1543258932,"by":{"name":"Alex Wilson","email":"alex@cooperi.net","username":"arekinath"}},{"type":"Integration-Approval","description":"Integration-Approval","value":"1","grantedOn":1543258932,"by":{"name":"Alex Wilson","email":"alex@cooperi.net","username":"arekinath"}},{"type":"SUBM","value":"1","grantedOn":1543266475,"by":{"name":"Trent Mick","email":"trentm@gmail.com","username":"trentm"}}],"files":[{"file":"/COMMIT_MSG","type":"ADDED","insertions":9,"deletions":0},{"file":"package.json","type":"MODIFIED","insertions":4,"deletions":-3}],"sizeInsertions":4,"sizeDeletions":-3},"patchSets":[{"number":"1","revision":"83e5a1e52e315cdbd7f07f988697f06e2ab07fe6","parents":["4d9be47aa0e74267e0211f566c07f6ddad566db6"],"ref":"refs/changes/15/5115/1","uploader":{"name":"Trent Mick","email":"trentm@gmail.com","username":"trentm"},"createdOn":1542940552,"author":{"name":"Trent Mick","email":"trentm@gmail.com","username":"trentm"},"isDraft":false,"kind":"REWORK","approvals":[{"type":"Code-Review","description":"Code-Review","value":"1","grantedOn":1543258932,"by":{"name":"Alex Wilson","email":"alex@cooperi.net","username":"arekinath"}},{"type":"Integration-Approval","description":"Integration-Approval","value":"1","grantedOn":1543258932,"by":{"name":"Alex Wilson","email":"alex@cooperi.net","username":"arekinath"}},{"type":"CI-Testing","description":"CI-Testing","value":"1","grantedOn":1542940583,"by":{"name":"Joyent Automation","username":"joyent-automation"}}],"files":[{"file":"/COMMIT_MSG","type":"ADDED","insertions":7,"deletions":0},{"file":"package.json","type":"MODIFIED","insertions":4,"deletions":-3}],"sizeInsertions":4,"sizeDeletions":-3},{"number":"2","revision":"f610b0aab574106f921c0e2c40fe0df10790ede5","parents":["4d9be47aa0e74267e0211f566c07f6ddad566db6"],"ref":"refs/changes/15/5115/2","uploader":{"name":"Trent Mick","email":"trentm@gmail.com","username":"trentm"},"createdOn":1543266469,"author":{"name":"Trent Mick","email":"trentm@gmail.com","username":"trentm"},"isDraft":false,"kind":"NO_CODE_CHANGE","approvals":[{"type":"Code-Review","description":"Code-Review","value":"1","grantedOn":1543258932,"by":{"name":"Alex Wilson","email":"alex@cooperi.net","username":"arekinath"}},{"type":"Integration-Approval","description":"Integration-Approval","value":"1","grantedOn":1543258932,"by":{"name":"Alex Wilson","email":"alex@cooperi.net","username":"arekinath"}},{"type":"CI-Testing","description":"CI-Testing","value":"1","grantedOn":1542940583,"by":{"name":"Joyent Automation","username":"joyent-automation"}},{"type":"SUBM","value":"1","grantedOn":1543266475,"by":{"name":"Trent Mick","email":"trentm@gmail.com","username":"trentm"}}],"files":[{"file":"/COMMIT_MSG","type":"ADDED","insertions":9,"deletions":0},{"file":"package.json","type":"MODIFIED","insertions":4,"deletions":-3}],"sizeInsertions":4,"sizeDeletions":-3}],"allReviewers":[{"name":"Alex Wilson","email":"alex@cooperi.net","username":"arekinath"},{"name":"Joyent Automation","username":"joyent-automation"},{"name":"Trent Mick","email":"trentm@gmail.com","username":"trentm"}]}