{"project":"joyent/mountain-gorilla","branch":"master","id":"I223a238a66cadc1772666582649ed196a302be4e","number":"1837","subject":"TOOLS-1758 MG: add TRITON jira project to list of eng projects for jira version update scripts","owner":{"name":"Trent Mick","email":"trentm@gmail.com","username":"trentm"},"url":"https://cr.joyent.us/1837","commitMessage":"TOOLS-1758 MG: add TRITON jira project to list of eng projects for jira version update scripts\n","createdOn":1493147842,"lastUpdated":1493148024,"open":false,"status":"MERGED","comments":[{"timestamp":1493147842,"reviewer":{"name":"Trent Mick","email":"trentm@gmail.com","username":"trentm"},"message":"Uploaded patch set 1."},{"timestamp":1493147843,"reviewer":{"name":"Trent Mick","email":"trentm@gmail.com","username":"trentm"},"message":"Patch Set 1:\n\nNew commits:\n    \n    commit bdf83df07f482d805b9d74280cff4517f7a9d054\n    \n    add TRITON jira project"},{"timestamp":1493147935,"reviewer":{"name":"Trent Mick","email":"trentm@gmail.com","username":"trentm"},"message":"Uploaded patch set 2."},{"timestamp":1493147936,"reviewer":{"name":"Trent Mick","email":"trentm@gmail.com","username":"trentm"},"message":"Patch Set 2:\n\nNew commits:\n    \n    commit 978a315b29382698a1d43a8811ec2634d8305a92\n    \n    update copyright date"},{"timestamp":1493147953,"reviewer":{"name":"Josh Wilsdon","email":"josh@wilsdon.ca","username":"joshwilsdon"},"message":"Patch Set 1:\n\n(1 comment)"},{"timestamp":1493147988,"reviewer":{"name":"Josh Wilsdon","email":"josh@wilsdon.ca","username":"joshwilsdon"},"message":"Patch Set 2: Code-Review+1 Integration-Approval+1"},{"timestamp":1493148024,"reviewer":{"name":"Gerrit Code Review","email":"no-reply@cr.joyent.us"},"message":"Change has been successfully merged by Trent Mick"}],"currentPatchSet":{"number":"2","revision":"223a238a66cadc1772666582649ed196a302be4e","parents":["3188b512c501ec306fe52882bad0592e2288812b"],"ref":"refs/changes/37/1837/2","uploader":{"name":"Trent Mick","email":"trentm@gmail.com","username":"trentm"},"createdOn":1493147935,"author":{"name":"Trent Mick","email":"trentm@gmail.com","username":"trentm"},"isDraft":false,"kind":"REWORK","approvals":[{"type":"Code-Review","description":"Code-Review","value":"1","grantedOn":1493147988,"by":{"name":"Josh Wilsdon","email":"josh@wilsdon.ca","username":"joshwilsdon"}},{"type":"Integration-Approval","description":"Integration-Approval","value":"1","grantedOn":1493147988,"by":{"name":"Josh Wilsdon","email":"josh@wilsdon.ca","username":"joshwilsdon"}},{"type":"SUBM","value":"1","grantedOn":1493148024,"by":{"name":"Trent Mick","email":"trentm@gmail.com","username":"trentm"}}],"files":[{"file":"/COMMIT_MSG","type":"ADDED","insertions":7,"deletions":0},{"file":"tools/jira/listengprojects.sh","type":"MODIFIED","insertions":2,"deletions":-1}],"sizeInsertions":2,"sizeDeletions":-1},"patchSets":[{"number":"1","revision":"4b198f59600202c228b04532e727a167fb3ce88c","parents":["3188b512c501ec306fe52882bad0592e2288812b"],"ref":"refs/changes/37/1837/1","uploader":{"name":"Trent Mick","email":"trentm@gmail.com","username":"trentm"},"createdOn":1493147842,"author":{"name":"Trent Mick","email":"trentm@gmail.com","username":"trentm"},"isDraft":false,"kind":"REWORK","comments":[{"file":"tools/jira/listengprojects.sh","line":9,"reviewer":{"name":"Josh Wilsdon","email":"josh@wilsdon.ca","username":"joshwilsdon"},"message":"2017"}],"files":[{"file":"/COMMIT_MSG","type":"ADDED","insertions":7,"deletions":0},{"file":"tools/jira/listengprojects.sh","type":"MODIFIED","insertions":1,"deletions":0}],"sizeInsertions":1,"sizeDeletions":0},{"number":"2","revision":"223a238a66cadc1772666582649ed196a302be4e","parents":["3188b512c501ec306fe52882bad0592e2288812b"],"ref":"refs/changes/37/1837/2","uploader":{"name":"Trent Mick","email":"trentm@gmail.com","username":"trentm"},"createdOn":1493147935,"author":{"name":"Trent Mick","email":"trentm@gmail.com","username":"trentm"},"isDraft":false,"kind":"REWORK","approvals":[{"type":"SUBM","value":"1","grantedOn":1493148024,"by":{"name":"Trent Mick","email":"trentm@gmail.com","username":"trentm"}},{"type":"Code-Review","description":"Code-Review","value":"1","grantedOn":1493147988,"by":{"name":"Josh Wilsdon","email":"josh@wilsdon.ca","username":"joshwilsdon"}},{"type":"Integration-Approval","description":"Integration-Approval","value":"1","grantedOn":1493147988,"by":{"name":"Josh Wilsdon","email":"josh@wilsdon.ca","username":"joshwilsdon"}}],"files":[{"file":"/COMMIT_MSG","type":"ADDED","insertions":7,"deletions":0},{"file":"tools/jira/listengprojects.sh","type":"MODIFIED","insertions":2,"deletions":-1}],"sizeInsertions":2,"sizeDeletions":-1}],"allReviewers":[{"name":"Trent Mick","email":"trentm@gmail.com","username":"trentm"},{"name":"Josh Wilsdon","email":"josh@wilsdon.ca","username":"joshwilsdon"}]}