{"project":"joyent/manta-marlin","branch":"master","id":"I8a80311c38dce010c25ac1541cda540130f809db","number":"5136","subject":"MANTA-4030 many images using node 0.10 or 0.12 broken by transitive lru-cache@4.1.4 dep","owner":{"name":"Trent Mick","email":"trentm@gmail.com","username":"trentm"},"url":"https://cr.joyent.us/5136","commitMessage":"MANTA-4030 many images using node 0.10 or 0.12 broken by transitive lru-cache@4.1.4 dep\n","createdOn":1543019920,"lastUpdated":1544127458,"open":false,"status":"ABANDONED","comments":[{"timestamp":1543019920,"reviewer":{"name":"Trent Mick","email":"trentm@gmail.com","username":"trentm"},"message":"Uploaded patch set 1."},{"timestamp":1543019921,"reviewer":{"name":"Trent Mick","email":"trentm@gmail.com","username":"trentm"},"message":"Patch Set 1:\n\nNew commits:\n    \n    commit 3359599127a0796cc4d029ecf24e43a44c9e03c8\n    \n    fix it"},{"timestamp":1543019970,"reviewer":{"name":"Joyent Automation","username":"joyent-automation"},"message":"Patch Set 1: CI-Testing+1\n\n\"make check\" passed ok"},{"timestamp":1543280050,"reviewer":{"name":"Trent Mick","email":"trentm@gmail.com","username":"trentm"},"message":"Uploaded patch set 2."},{"timestamp":1543280052,"reviewer":{"name":"Trent Mick","email":"trentm@gmail.com","username":"trentm"},"message":"Patch Set 2:\n\nNew commits:\n    \n    commit 22de9956f699ebf7bb8cc1e538461d0f3f09c079\n    \n    the package.json for the agent and the VM image is where we want to pin"},{"timestamp":1543280095,"reviewer":{"name":"Joyent Automation","username":"joyent-automation"},"message":"Patch Set 2: CI-Testing+1\n\n\"make check\" passed ok"},{"timestamp":1543280166,"reviewer":{"name":"Trent Mick","email":"trentm@gmail.com","username":"trentm"},"message":"Patch Set 2:\n\n@alex: I\u0027ve switch the lru-cache pinning to the dev/package.json (for the marlin agent and the jobsupervisor image) and am rebuilding those:\n\n```\n$ launch-build -t grr-MANTA-4030 jobsupervisor\nBuilding jobsupervisor with TRY_BRANCH\u003dgrr-MANTA-4030\n```"},{"timestamp":1544127458,"reviewer":{"name":"Trent Mick","email":"trentm@gmail.com","username":"trentm"},"message":"Abandoned\n\nlru-cache@4.1.5 release fixes the issue without requiring us to pin to 4.1.3"}],"currentPatchSet":{"number":"2","revision":"8a80311c38dce010c25ac1541cda540130f809db","parents":["93325715daf76c232b93a82833a5f28870fd1581"],"ref":"refs/changes/36/5136/2","uploader":{"name":"Trent Mick","email":"trentm@gmail.com","username":"trentm"},"createdOn":1543280050,"author":{"name":"Trent Mick","email":"trentm@gmail.com","username":"trentm"},"isDraft":false,"kind":"REWORK","approvals":[{"type":"CI-Testing","description":"CI-Testing","value":"1","grantedOn":1543280095,"by":{"name":"Joyent Automation","username":"joyent-automation"}}],"files":[{"file":"/COMMIT_MSG","type":"ADDED","insertions":7,"deletions":0},{"file":"dev/package.json","type":"MODIFIED","insertions":3,"deletions":-1}],"sizeInsertions":3,"sizeDeletions":-1},"patchSets":[{"number":"1","revision":"9f1971ddac5c7d13b5d249213c98caaed9cc32d2","parents":["93325715daf76c232b93a82833a5f28870fd1581"],"ref":"refs/changes/36/5136/1","uploader":{"name":"Trent Mick","email":"trentm@gmail.com","username":"trentm"},"createdOn":1543019920,"author":{"name":"Trent Mick","email":"trentm@gmail.com","username":"trentm"},"isDraft":false,"kind":"REWORK","approvals":[{"type":"CI-Testing","description":"CI-Testing","value":"1","grantedOn":1543019970,"by":{"name":"Joyent Automation","username":"joyent-automation"}}],"files":[{"file":"/COMMIT_MSG","type":"ADDED","insertions":7,"deletions":0},{"file":"package.json","type":"MODIFIED","insertions":3,"deletions":-1}],"sizeInsertions":3,"sizeDeletions":-1},{"number":"2","revision":"8a80311c38dce010c25ac1541cda540130f809db","parents":["93325715daf76c232b93a82833a5f28870fd1581"],"ref":"refs/changes/36/5136/2","uploader":{"name":"Trent Mick","email":"trentm@gmail.com","username":"trentm"},"createdOn":1543280050,"author":{"name":"Trent Mick","email":"trentm@gmail.com","username":"trentm"},"isDraft":false,"kind":"REWORK","approvals":[{"type":"CI-Testing","description":"CI-Testing","value":"1","grantedOn":1543280095,"by":{"name":"Joyent Automation","username":"joyent-automation"}}],"files":[{"file":"/COMMIT_MSG","type":"ADDED","insertions":7,"deletions":0},{"file":"dev/package.json","type":"MODIFIED","insertions":3,"deletions":-1}],"sizeInsertions":3,"sizeDeletions":-1}],"allReviewers":[{"name":"Joyent Automation","username":"joyent-automation"},{"name":"Trent Mick","email":"trentm@gmail.com","username":"trentm"},{"name":"Alex Wilson","email":"alex@cooperi.net","username":"arekinath"}]}