{"project":"joyent/illumos-joyent","branch":"master","id":"I6a16bb6f8fc6827fcaf53a8052b197238adeb300","number":"1826","subject":"OS-6070 mdb inserts spurious newlines in wrapped input lines Reviewed by: Joshua M. Clulow \u003cjmc@joyent.com\u003e Reviewed by: Dave Pacheco \u003cdap@joyent.com\u003e Approved by: Robert Mustacchi \u003crm@joyent.com\u003e","owner":{"name":"Bryan Cantrill","email":"bryan@joyent.com","username":"bcantrill"},"url":"https://cr.joyent.us/1826","commitMessage":"OS-6070 mdb inserts spurious newlines in wrapped input lines\nReviewed by: Joshua M. Clulow \u003cjmc@joyent.com\u003e\nReviewed by: Dave Pacheco \u003cdap@joyent.com\u003e\nApproved by: Robert Mustacchi \u003crm@joyent.com\u003e\n","createdOn":1492821253,"lastUpdated":1493070745,"open":false,"status":"MERGED","comments":[{"timestamp":1492821253,"reviewer":{"name":"Bryan Cantrill","email":"bryan@joyent.com","username":"bcantrill"},"message":"Uploaded patch set 1."},{"timestamp":1493066997,"reviewer":{"name":"David Pacheco","email":"dap@joyent.com","username":"davepacheco"},"message":"Patch Set 1: Code-Review+1"},{"timestamp":1493067752,"reviewer":{"name":"Joshua M. Clulow","email":"jmc@joyent.com","username":"jclulow"},"message":"Patch Set 1: Code-Review+1"},{"timestamp":1493069366,"reviewer":{"name":"Robert Mustacchi","email":"rm+illumos@fingolfin.org","username":"rmustacc"},"message":"Patch Set 1: Integration-Approval+1"},{"timestamp":1493070698,"reviewer":{"name":"Bryan Cantrill","email":"bryan@joyent.com","username":"bcantrill"},"message":"Patch Set 2: Commit message was updated."},{"timestamp":1493070721,"reviewer":{"name":"Bryan Cantrill","email":"bryan@joyent.com","username":"bcantrill"},"message":"Patch Set 3: Patch Set 2 was rebased"},{"timestamp":1493070745,"reviewer":{"name":"Gerrit Code Review","email":"no-reply@cr.joyent.us"},"message":"Change has been successfully merged by Bryan Cantrill"}],"currentPatchSet":{"number":"3","revision":"e12d340399f1171b85e17ae6ff8fe3eba80d8706","parents":["920ae1400e6245bf6c0ed9d43da5b20b80cbc8a3"],"ref":"refs/changes/26/1826/3","uploader":{"name":"Bryan Cantrill","email":"bryan@joyent.com","username":"bcantrill"},"createdOn":1493070721,"author":{"name":"Bryan Cantrill","email":"bryan@joyent.com","username":"bcantrill"},"isDraft":false,"kind":"TRIVIAL_REBASE","approvals":[{"type":"Code-Review","description":"Code-Review","value":"1","grantedOn":1493066997,"by":{"name":"David Pacheco","email":"dap@joyent.com","username":"davepacheco"}},{"type":"Code-Review","description":"Code-Review","value":"1","grantedOn":1493067752,"by":{"name":"Joshua M. Clulow","email":"jmc@joyent.com","username":"jclulow"}},{"type":"Integration-Approval","description":"Integration-Approval","value":"1","grantedOn":1493069366,"by":{"name":"Robert Mustacchi","email":"rm+illumos@fingolfin.org","username":"rmustacc"}},{"type":"SUBM","value":"1","grantedOn":1493070745,"by":{"name":"Bryan Cantrill","email":"bryan@joyent.com","username":"bcantrill"}}],"files":[{"file":"/COMMIT_MSG","type":"ADDED","insertions":10,"deletions":0},{"file":"usr/src/cmd/mdb/common/mdb/mdb_termio.c","type":"MODIFIED","insertions":96,"deletions":-7}],"sizeInsertions":96,"sizeDeletions":-7},"patchSets":[{"number":"1","revision":"6a16bb6f8fc6827fcaf53a8052b197238adeb300","parents":["6f1d54d1657b9c469ae08d5ee733e114fe36c690"],"ref":"refs/changes/26/1826/1","uploader":{"name":"Bryan Cantrill","email":"bryan@joyent.com","username":"bcantrill"},"createdOn":1492821253,"author":{"name":"Bryan Cantrill","email":"bryan@joyent.com","username":"bcantrill"},"isDraft":false,"kind":"REWORK","approvals":[{"type":"Code-Review","description":"Code-Review","value":"1","grantedOn":1493066997,"by":{"name":"David Pacheco","email":"dap@joyent.com","username":"davepacheco"}},{"type":"Integration-Approval","description":"Integration-Approval","value":"1","grantedOn":1493069366,"by":{"name":"Robert Mustacchi","email":"rm+illumos@fingolfin.org","username":"rmustacc"}},{"type":"Code-Review","description":"Code-Review","value":"1","grantedOn":1493067752,"by":{"name":"Joshua M. Clulow","email":"jmc@joyent.com","username":"jclulow"}}],"files":[{"file":"/COMMIT_MSG","type":"ADDED","insertions":7,"deletions":0},{"file":"usr/src/cmd/mdb/common/mdb/mdb_termio.c","type":"MODIFIED","insertions":96,"deletions":-7}],"sizeInsertions":96,"sizeDeletions":-7},{"number":"2","revision":"c79379afab8246d71ad16ada76b26276280a4ca5","parents":["6f1d54d1657b9c469ae08d5ee733e114fe36c690"],"ref":"refs/changes/26/1826/2","uploader":{"name":"Bryan Cantrill","email":"bryan@joyent.com","username":"bcantrill"},"createdOn":1493070698,"author":{"name":"Bryan Cantrill","email":"bryan@joyent.com","username":"bcantrill"},"isDraft":false,"kind":"NO_CODE_CHANGE","approvals":[{"type":"Code-Review","description":"Code-Review","value":"1","grantedOn":1493066997,"by":{"name":"David Pacheco","email":"dap@joyent.com","username":"davepacheco"}},{"type":"Integration-Approval","description":"Integration-Approval","value":"1","grantedOn":1493069366,"by":{"name":"Robert Mustacchi","email":"rm+illumos@fingolfin.org","username":"rmustacc"}},{"type":"Code-Review","description":"Code-Review","value":"1","grantedOn":1493067752,"by":{"name":"Joshua M. Clulow","email":"jmc@joyent.com","username":"jclulow"}}],"files":[{"file":"/COMMIT_MSG","type":"ADDED","insertions":10,"deletions":0},{"file":"usr/src/cmd/mdb/common/mdb/mdb_termio.c","type":"MODIFIED","insertions":96,"deletions":-7}],"sizeInsertions":96,"sizeDeletions":-7},{"number":"3","revision":"e12d340399f1171b85e17ae6ff8fe3eba80d8706","parents":["920ae1400e6245bf6c0ed9d43da5b20b80cbc8a3"],"ref":"refs/changes/26/1826/3","uploader":{"name":"Bryan Cantrill","email":"bryan@joyent.com","username":"bcantrill"},"createdOn":1493070721,"author":{"name":"Bryan Cantrill","email":"bryan@joyent.com","username":"bcantrill"},"isDraft":false,"kind":"TRIVIAL_REBASE","approvals":[{"type":"Code-Review","description":"Code-Review","value":"1","grantedOn":1493066997,"by":{"name":"David Pacheco","email":"dap@joyent.com","username":"davepacheco"}},{"type":"Integration-Approval","description":"Integration-Approval","value":"1","grantedOn":1493069366,"by":{"name":"Robert Mustacchi","email":"rm+illumos@fingolfin.org","username":"rmustacc"}},{"type":"Code-Review","description":"Code-Review","value":"1","grantedOn":1493067752,"by":{"name":"Joshua M. Clulow","email":"jmc@joyent.com","username":"jclulow"}},{"type":"SUBM","value":"1","grantedOn":1493070745,"by":{"name":"Bryan Cantrill","email":"bryan@joyent.com","username":"bcantrill"}}],"files":[{"file":"/COMMIT_MSG","type":"ADDED","insertions":10,"deletions":0},{"file":"usr/src/cmd/mdb/common/mdb/mdb_termio.c","type":"MODIFIED","insertions":96,"deletions":-7}],"sizeInsertions":96,"sizeDeletions":-7}],"allReviewers":[{"name":"David Pacheco","email":"dap@joyent.com","username":"davepacheco"},{"name":"Robert Mustacchi","email":"rm+illumos@fingolfin.org","username":"rmustacc"},{"name":"Joshua M. Clulow","email":"jmc@joyent.com","username":"jclulow"},{"name":"Bryan Cantrill","email":"bryan@joyent.com","username":"bcantrill"}]}