{"project":"joyent/node-manta","branch":"master","id":"I620ea803d2df7ad5681f0f95be4a5babdee1dc64","number":"2788","subject":"joyent/node-manta#332 Add support for Content-Encoding for objects","owner":{"name":"Jan Wyszynski","email":"jan.wyszynski@joyent.com","username":"IanWyszynski"},"url":"https://cr.joyent.us/2788","commitMessage":"joyent/node-manta#332 Add support for Content-Encoding for objects\n","createdOn":1508178740,"lastUpdated":1508180391,"open":false,"status":"ABANDONED","comments":[{"timestamp":1508178740,"reviewer":{"name":"Jan Wyszynski","email":"jan.wyszynski@joyent.com","username":"IanWyszynski"},"message":"Uploaded patch set 1."},{"timestamp":1508178767,"reviewer":{"name":"Joyent Automation","username":"joyent-automation"},"message":"Patch Set 1: CI-Testing+1\n\n\"make check\" passed ok"},{"timestamp":1508180391,"reviewer":{"name":"Jan Wyszynski","email":"jan.wyszynski@joyent.com","username":"IanWyszynski"},"message":"Abandoned\n\nwant to revisit this change when the necessary muskie change has been made."}],"currentPatchSet":{"number":"1","revision":"620ea803d2df7ad5681f0f95be4a5babdee1dc64","parents":["db26e1bc598de7e9b1fc20649f03cf9d2b4bc272"],"ref":"refs/changes/88/2788/1","uploader":{"name":"Jan Wyszynski","email":"jan.wyszynski@joyent.com","username":"IanWyszynski"},"createdOn":1508178740,"author":{"name":"Jan Wyszynski","email":"jan.wyszynski@joyent.com","username":"IanWyszynski"},"isDraft":false,"kind":"REWORK","approvals":[{"type":"CI-Testing","description":"CI-Testing","value":"1","grantedOn":1508178767,"by":{"name":"Joyent Automation","username":"joyent-automation"}}],"files":[{"file":"/COMMIT_MSG","type":"ADDED","insertions":7,"deletions":0},{"file":"bin/mmpu","type":"MODIFIED","insertions":2,"deletions":-1},{"file":"lib/client.js","type":"MODIFIED","insertions":5,"deletions":0}],"sizeInsertions":7,"sizeDeletions":-1},"patchSets":[{"number":"1","revision":"620ea803d2df7ad5681f0f95be4a5babdee1dc64","parents":["db26e1bc598de7e9b1fc20649f03cf9d2b4bc272"],"ref":"refs/changes/88/2788/1","uploader":{"name":"Jan Wyszynski","email":"jan.wyszynski@joyent.com","username":"IanWyszynski"},"createdOn":1508178740,"author":{"name":"Jan Wyszynski","email":"jan.wyszynski@joyent.com","username":"IanWyszynski"},"isDraft":false,"kind":"REWORK","approvals":[{"type":"CI-Testing","description":"CI-Testing","value":"1","grantedOn":1508178767,"by":{"name":"Joyent Automation","username":"joyent-automation"}}],"files":[{"file":"/COMMIT_MSG","type":"ADDED","insertions":7,"deletions":0},{"file":"bin/mmpu","type":"MODIFIED","insertions":2,"deletions":-1},{"file":"lib/client.js","type":"MODIFIED","insertions":5,"deletions":0}],"sizeInsertions":7,"sizeDeletions":-1}],"allReviewers":[{"name":"Joyent Automation","username":"joyent-automation"}]}