{"project":"joyent/smartos-live","branch":"master","id":"I012bd031e06c77f2d1e515f6a9bd53be41e0a5da","number":"357","subject":"OS-5634 system-log SMF method has existential confusion Reviewed by: Alex Wilson \u003calex.wilson@joyent.com\u003e Reviewed by: Josh Wilsdon \u003cjwilsdon@joyent.com\u003e","owner":{"name":"Brian Bennett","email":"brian.bennett@joyent.com","username":"bahamat"},"url":"https://cr.joyent.us/357","commitMessage":"OS-5634 system-log SMF method has existential confusion\nReviewed by: Alex Wilson \u003calex.wilson@joyent.com\u003e\nReviewed by: Josh Wilsdon \u003cjwilsdon@joyent.com\u003e\n","createdOn":1472244688,"lastUpdated":1472750536,"open":false,"status":"MERGED","comments":[{"timestamp":1472244688,"reviewer":{"name":"Brian Bennett","email":"brian.bennett@joyent.com","username":"bahamat"},"message":"Uploaded patch set 1."},{"timestamp":1472244732,"reviewer":{"name":"Joyent Automation","username":"joyent-automation"},"message":"Patch Set 1: CI-Testing+1\n\n\"make check\" passed ok"},{"timestamp":1472244923,"reviewer":{"name":"Alex Wilson","email":"alex@cooperi.net","username":"arekinath"},"message":"Patch Set 1:\n\n(1 comment)"},{"timestamp":1472244923,"reviewer":{"name":"Brian Bennett","email":"brian.bennett@joyent.com","username":"bahamat"},"message":"Uploaded patch set 2."},{"timestamp":1472244966,"reviewer":{"name":"Joyent Automation","username":"joyent-automation"},"message":"Patch Set 2: CI-Testing+1\n\n\"make check\" passed ok"},{"timestamp":1472245092,"reviewer":{"name":"Brian Bennett","email":"brian.bennett@joyent.com","username":"bahamat"},"message":"Uploaded patch set 3: Commit message was updated."},{"timestamp":1472245286,"reviewer":{"name":"Brian Bennett","email":"brian.bennett@joyent.com","username":"bahamat"},"message":"Uploaded patch set 4."},{"timestamp":1472245339,"reviewer":{"name":"Joyent Automation","username":"joyent-automation"},"message":"Patch Set 4: CI-Testing+1\n\n\"make check\" passed ok"},{"timestamp":1472245832,"reviewer":{"name":"Alex Wilson","email":"alex@cooperi.net","username":"arekinath"},"message":"Patch Set 5: Commit message was updated."},{"timestamp":1472245837,"reviewer":{"name":"Alex Wilson","email":"alex@cooperi.net","username":"arekinath"},"message":"Patch Set 5: Code-Review+1"},{"timestamp":1472245997,"reviewer":{"name":"Brian Bennett","email":"brian.bennett@joyent.com","username":"bahamat"},"message":"Uploaded patch set 6: Commit message was updated."},{"timestamp":1472246201,"reviewer":{"name":"Josh Wilsdon","email":"josh@wilsdon.ca","username":"joshwilsdon"},"message":"Patch Set 5:\n\n(2 comments)"},{"timestamp":1472246332,"reviewer":{"name":"Brian Bennett","email":"brian.bennett@joyent.com","username":"bahamat"},"message":"Uploaded patch set 7."},{"timestamp":1472246373,"reviewer":{"name":"Joyent Automation","username":"joyent-automation"},"message":"Patch Set 7: CI-Testing+1\n\n\"make check\" passed ok"},{"timestamp":1472246394,"reviewer":{"name":"Brian Bennett","email":"brian.bennett@joyent.com","username":"bahamat"},"message":"Uploaded patch set 8."},{"timestamp":1472246437,"reviewer":{"name":"Joyent Automation","username":"joyent-automation"},"message":"Patch Set 8: CI-Testing+1\n\n\"make check\" passed ok"},{"timestamp":1472246650,"reviewer":{"name":"Brian Bennett","email":"brian.bennett@joyent.com","username":"bahamat"},"message":"Uploaded patch set 9."},{"timestamp":1472246697,"reviewer":{"name":"Joyent Automation","username":"joyent-automation"},"message":"Patch Set 9: CI-Testing+1\n\n\"make check\" passed ok"},{"timestamp":1472246713,"reviewer":{"name":"Brian Bennett","email":"brian.bennett@joyent.com","username":"bahamat"},"message":"Patch Set 5:\n\n(2 comments)"},{"timestamp":1472750049,"reviewer":{"name":"Brian Bennett","email":"brian.bennett@joyent.com","username":"bahamat"},"message":"Uploaded patch set 10: Patch Set 9 was rebased."},{"timestamp":1472750088,"reviewer":{"name":"Joyent Automation","username":"joyent-automation"},"message":"Patch Set 10:\n\n\"make check\" passed ok"},{"timestamp":1472750253,"reviewer":{"name":"Josh Wilsdon","email":"josh@wilsdon.ca","username":"joshwilsdon"},"message":"Patch Set 10: Code-Review+1\n\n(1 comment)"},{"timestamp":1472750533,"reviewer":{"name":"Brian Bennett","email":"brian.bennett@joyent.com","username":"bahamat"},"message":"Patch Set 10: Integration-Approval+1"},{"timestamp":1472750536,"reviewer":{"name":"Gerrit Code Review","email":"no-reply@cr.joyent.us"},"message":"Change has been successfully merged by Brian Bennett"}],"currentPatchSet":{"number":"10","revision":"012bd031e06c77f2d1e515f6a9bd53be41e0a5da","parents":["9d03f1909e3e14ce94ca413adf1f0f3d8d343853"],"ref":"refs/changes/57/357/10","uploader":{"name":"Brian Bennett","email":"brian.bennett@joyent.com","username":"bahamat"},"createdOn":1472750049,"author":{"name":"Brian Bennett","email":"brian.bennett@joyent.com","username":"bahamat"},"isDraft":false,"kind":"TRIVIAL_REBASE","approvals":[{"type":"CI-Testing","description":"CI-Testing","value":"1","grantedOn":1472246697,"by":{"name":"Joyent Automation","username":"joyent-automation"}},{"type":"Code-Review","description":"Code-Review","value":"1","grantedOn":1472750253,"by":{"name":"Josh Wilsdon","email":"josh@wilsdon.ca","username":"joshwilsdon"}},{"type":"Integration-Approval","description":"Integration-Approval","value":"1","grantedOn":1472750533,"by":{"name":"Brian Bennett","email":"brian.bennett@joyent.com","username":"bahamat"}},{"type":"SUBM","value":"1","grantedOn":1472750536,"by":{"name":"Brian Bennett","email":"brian.bennett@joyent.com","username":"bahamat"}}],"comments":[{"file":"overlay/generic/lib/svc/method/system-log","line":120,"reviewer":{"name":"Josh Wilsdon","email":"josh@wilsdon.ca","username":"joshwilsdon"},"message":"\"Executable /usr/sbin/syslogd not found or not executable.\" sounds redundantly redundant."}],"files":[{"file":"/COMMIT_MSG","type":"ADDED","insertions":9,"deletions":0},{"file":"overlay/generic/lib/svc/method/system-log","type":"MODIFIED","insertions":4,"deletions":-3}],"sizeInsertions":4,"sizeDeletions":-3},"patchSets":[{"number":"1","revision":"39d1ca5dacefce55792c4ab69842cfc49cd69b84","parents":["542f022db1666b2d306c740fa9818f58461695bc"],"ref":"refs/changes/57/357/1","uploader":{"name":"Brian Bennett","email":"brian.bennett@joyent.com","username":"bahamat"},"createdOn":1472244688,"author":{"name":"Brian Bennett","email":"brian.bennett@joyent.com","username":"bahamat"},"isDraft":false,"kind":"REWORK","approvals":[{"type":"CI-Testing","description":"CI-Testing","value":"1","grantedOn":1472244732,"by":{"name":"Joyent Automation","username":"joyent-automation"}}],"comments":[{"file":"overlay/generic/lib/svc/method/system-log","line":113,"reviewer":{"name":"Alex Wilson","email":"alex@cooperi.net","username":"arekinath"},"message":"Tabs please! :)"}],"files":[{"file":"/COMMIT_MSG","type":"ADDED","insertions":7,"deletions":0},{"file":"overlay/generic/lib/svc/method/system-log","type":"MODIFIED","insertions":3,"deletions":-2}],"sizeInsertions":3,"sizeDeletions":-2},{"number":"2","revision":"68074232066db28cfe0b033489dc03ed8f9c3dbb","parents":["542f022db1666b2d306c740fa9818f58461695bc"],"ref":"refs/changes/57/357/2","uploader":{"name":"Brian Bennett","email":"brian.bennett@joyent.com","username":"bahamat"},"createdOn":1472244923,"author":{"name":"Brian Bennett","email":"brian.bennett@joyent.com","username":"bahamat"},"isDraft":false,"kind":"REWORK","approvals":[{"type":"CI-Testing","description":"CI-Testing","value":"1","grantedOn":1472244966,"by":{"name":"Joyent Automation","username":"joyent-automation"}}],"files":[{"file":"/COMMIT_MSG","type":"ADDED","insertions":7,"deletions":0},{"file":"overlay/generic/lib/svc/method/system-log","type":"MODIFIED","insertions":3,"deletions":-2}],"sizeInsertions":3,"sizeDeletions":-2},{"number":"3","revision":"e3fb0259553bbdc223e7085ef5ebddba7897b26a","parents":["542f022db1666b2d306c740fa9818f58461695bc"],"ref":"refs/changes/57/357/3","uploader":{"name":"Brian Bennett","email":"brian.bennett@joyent.com","username":"bahamat"},"createdOn":1472245092,"author":{"name":"Brian Bennett","email":"brian.bennett@joyent.com","username":"bahamat"},"isDraft":false,"kind":"NO_CODE_CHANGE","approvals":[{"type":"CI-Testing","description":"CI-Testing","value":"1","grantedOn":1472244966,"by":{"name":"Joyent Automation","username":"joyent-automation"}}],"files":[{"file":"/COMMIT_MSG","type":"ADDED","insertions":9,"deletions":0},{"file":"overlay/generic/lib/svc/method/system-log","type":"MODIFIED","insertions":3,"deletions":-2}],"sizeInsertions":3,"sizeDeletions":-2},{"number":"4","revision":"a6c3c9f0464c2d7aa71ddab4fd74c535dc86c6e5","parents":["542f022db1666b2d306c740fa9818f58461695bc"],"ref":"refs/changes/57/357/4","uploader":{"name":"Brian Bennett","email":"brian.bennett@joyent.com","username":"bahamat"},"createdOn":1472245286,"author":{"name":"Brian Bennett","email":"brian.bennett@joyent.com","username":"bahamat"},"isDraft":false,"kind":"REWORK","approvals":[{"type":"CI-Testing","description":"CI-Testing","value":"1","grantedOn":1472245339,"by":{"name":"Joyent Automation","username":"joyent-automation"}}],"files":[{"file":"/COMMIT_MSG","type":"ADDED","insertions":9,"deletions":0},{"file":"overlay/generic/lib/svc/method/system-log","type":"MODIFIED","insertions":3,"deletions":-2}],"sizeInsertions":3,"sizeDeletions":-2},{"number":"5","revision":"0fbdc62eafc7b3ef34ea6e0231e7b1a1430d2cd8","parents":["542f022db1666b2d306c740fa9818f58461695bc"],"ref":"refs/changes/57/357/5","uploader":{"name":"Brian Bennett","email":"brian.bennett@joyent.com","username":"bahamat"},"createdOn":1472245832,"author":{"name":"Brian Bennett","email":"brian.bennett@joyent.com","username":"bahamat"},"isDraft":false,"kind":"NO_CODE_CHANGE","approvals":[{"type":"Code-Review","description":"Code-Review","value":"1","grantedOn":1472245837,"by":{"name":"Alex Wilson","email":"alex@cooperi.net","username":"arekinath"}},{"type":"CI-Testing","description":"CI-Testing","value":"1","grantedOn":1472245339,"by":{"name":"Joyent Automation","username":"joyent-automation"}}],"comments":[{"file":"overlay/generic/lib/svc/method/system-log","line":106,"reviewer":{"name":"Josh Wilsdon","email":"josh@wilsdon.ca","username":"joshwilsdon"},"message":"Perhaps consider \"/usr/sbin/rsyslogd is not found or not executable.\" instead? Just to prevent the case where someone sees the message \"not found\" and goes and looks and finds that the file *is* there, and then needs to dig through the source before they realize what this means."},{"file":"overlay/generic/lib/svc/method/system-log","line":106,"reviewer":{"name":"Brian Bennett","email":"brian.bennett@joyent.com","username":"bahamat"},"message":"Done"},{"file":"overlay/generic/lib/svc/method/system-log","line":120,"reviewer":{"name":"Josh Wilsdon","email":"josh@wilsdon.ca","username":"joshwilsdon"},"message":"Same as above."},{"file":"overlay/generic/lib/svc/method/system-log","line":120,"reviewer":{"name":"Brian Bennett","email":"brian.bennett@joyent.com","username":"bahamat"},"message":"Done"}],"files":[{"file":"/COMMIT_MSG","type":"ADDED","insertions":9,"deletions":0},{"file":"overlay/generic/lib/svc/method/system-log","type":"MODIFIED","insertions":3,"deletions":-2}],"sizeInsertions":3,"sizeDeletions":-2},{"number":"6","revision":"f6c72fe84c8e643a818d15ce45d60cefdd938cde","parents":["542f022db1666b2d306c740fa9818f58461695bc"],"ref":"refs/changes/57/357/6","uploader":{"name":"Brian Bennett","email":"brian.bennett@joyent.com","username":"bahamat"},"createdOn":1472245997,"author":{"name":"Brian Bennett","email":"brian.bennett@joyent.com","username":"bahamat"},"isDraft":false,"kind":"NO_CODE_CHANGE","approvals":[{"type":"Code-Review","description":"Code-Review","value":"1","grantedOn":1472245837,"by":{"name":"Alex Wilson","email":"alex@cooperi.net","username":"arekinath"}},{"type":"CI-Testing","description":"CI-Testing","value":"1","grantedOn":1472245339,"by":{"name":"Joyent Automation","username":"joyent-automation"}}],"files":[{"file":"/COMMIT_MSG","type":"ADDED","insertions":9,"deletions":0},{"file":"overlay/generic/lib/svc/method/system-log","type":"MODIFIED","insertions":3,"deletions":-2}],"sizeInsertions":3,"sizeDeletions":-2},{"number":"7","revision":"10e5ea6d3390b4dcfd7eea8a54b3396ba222cb5a","parents":["542f022db1666b2d306c740fa9818f58461695bc"],"ref":"refs/changes/57/357/7","uploader":{"name":"Brian Bennett","email":"brian.bennett@joyent.com","username":"bahamat"},"createdOn":1472246332,"author":{"name":"Brian Bennett","email":"brian.bennett@joyent.com","username":"bahamat"},"isDraft":false,"kind":"REWORK","approvals":[{"type":"CI-Testing","description":"CI-Testing","value":"1","grantedOn":1472246373,"by":{"name":"Joyent Automation","username":"joyent-automation"}}],"files":[{"file":"/COMMIT_MSG","type":"ADDED","insertions":9,"deletions":0},{"file":"overlay/generic/lib/svc/method/system-log","type":"MODIFIED","insertions":3,"deletions":-2}],"sizeInsertions":3,"sizeDeletions":-2},{"number":"8","revision":"2ea0bfdf47bd703e99d8fb35f6fe5ff4706cba40","parents":["542f022db1666b2d306c740fa9818f58461695bc"],"ref":"refs/changes/57/357/8","uploader":{"name":"Brian Bennett","email":"brian.bennett@joyent.com","username":"bahamat"},"createdOn":1472246394,"author":{"name":"Brian Bennett","email":"brian.bennett@joyent.com","username":"bahamat"},"isDraft":false,"kind":"REWORK","approvals":[{"type":"CI-Testing","description":"CI-Testing","value":"1","grantedOn":1472246437,"by":{"name":"Joyent Automation","username":"joyent-automation"}}],"files":[{"file":"/COMMIT_MSG","type":"ADDED","insertions":9,"deletions":0},{"file":"overlay/generic/lib/svc/method/system-log","type":"MODIFIED","insertions":4,"deletions":-3}],"sizeInsertions":4,"sizeDeletions":-3},{"number":"9","revision":"cc401beed2bd4ad037ab0fe7e20b49af0d5ae9e1","parents":["542f022db1666b2d306c740fa9818f58461695bc"],"ref":"refs/changes/57/357/9","uploader":{"name":"Brian Bennett","email":"brian.bennett@joyent.com","username":"bahamat"},"createdOn":1472246650,"author":{"name":"Brian Bennett","email":"brian.bennett@joyent.com","username":"bahamat"},"isDraft":false,"kind":"REWORK","approvals":[{"type":"CI-Testing","description":"CI-Testing","value":"1","grantedOn":1472246697,"by":{"name":"Joyent Automation","username":"joyent-automation"}}],"files":[{"file":"/COMMIT_MSG","type":"ADDED","insertions":9,"deletions":0},{"file":"overlay/generic/lib/svc/method/system-log","type":"MODIFIED","insertions":4,"deletions":-3}],"sizeInsertions":4,"sizeDeletions":-3},{"number":"10","revision":"012bd031e06c77f2d1e515f6a9bd53be41e0a5da","parents":["9d03f1909e3e14ce94ca413adf1f0f3d8d343853"],"ref":"refs/changes/57/357/10","uploader":{"name":"Brian Bennett","email":"brian.bennett@joyent.com","username":"bahamat"},"createdOn":1472750049,"author":{"name":"Brian Bennett","email":"brian.bennett@joyent.com","username":"bahamat"},"isDraft":false,"kind":"TRIVIAL_REBASE","approvals":[{"type":"CI-Testing","description":"CI-Testing","value":"1","grantedOn":1472246697,"by":{"name":"Joyent Automation","username":"joyent-automation"}},{"type":"Code-Review","description":"Code-Review","value":"1","grantedOn":1472750253,"by":{"name":"Josh Wilsdon","email":"josh@wilsdon.ca","username":"joshwilsdon"}},{"type":"Integration-Approval","description":"Integration-Approval","value":"1","grantedOn":1472750533,"by":{"name":"Brian Bennett","email":"brian.bennett@joyent.com","username":"bahamat"}},{"type":"SUBM","value":"1","grantedOn":1472750536,"by":{"name":"Brian Bennett","email":"brian.bennett@joyent.com","username":"bahamat"}}],"comments":[{"file":"overlay/generic/lib/svc/method/system-log","line":120,"reviewer":{"name":"Josh Wilsdon","email":"josh@wilsdon.ca","username":"joshwilsdon"},"message":"\"Executable /usr/sbin/syslogd not found or not executable.\" sounds redundantly redundant."}],"files":[{"file":"/COMMIT_MSG","type":"ADDED","insertions":9,"deletions":0},{"file":"overlay/generic/lib/svc/method/system-log","type":"MODIFIED","insertions":4,"deletions":-3}],"sizeInsertions":4,"sizeDeletions":-3}],"allReviewers":[{"name":"Joyent Automation","username":"joyent-automation"},{"name":"Alex Wilson","email":"alex@cooperi.net","username":"arekinath"},{"name":"Josh Wilsdon","email":"josh@wilsdon.ca","username":"joshwilsdon"},{"name":"Brian Bennett","email":"brian.bennett@joyent.com","username":"bahamat"}]}