{"project":"joyent/illumos-joyent","branch":"master","id":"I906f8ed317b42ef0ffba1b8885df6c62443a6de8","number":"6186","subject":"OS-7779 zoneadmd calls logstream_write with negative message length Reviewed by: Patrick Mooney \u003cpatrick.mooney@joyent.com\u003e Reviewed by: Jerry Jelinek \u003cjerry.jelinek@joyent.com\u003e Approved by: Jerry Jelinek \u003cjerry.jelinek@joyent.com\u003e","owner":{"name":"Mike Gerdts","email":"mike.gerdts@joyent.com","username":"mgerdts"},"url":"https://cr.joyent.us/6186","commitMessage":"OS-7779 zoneadmd calls logstream_write with negative message length\nReviewed by: Patrick Mooney \u003cpatrick.mooney@joyent.com\u003e\nReviewed by: Jerry Jelinek \u003cjerry.jelinek@joyent.com\u003e\nApproved by: Jerry Jelinek \u003cjerry.jelinek@joyent.com\u003e\n","createdOn":1556749311,"lastUpdated":1556826587,"open":false,"status":"MERGED","comments":[{"timestamp":1556749311,"reviewer":{"name":"Mike Gerdts","email":"mike.gerdts@joyent.com","username":"mgerdts"},"message":"Uploaded patch set 1."},{"timestamp":1556749579,"reviewer":{"name":"Jerry Jelinek","email":"jerry.jelinek@joyent.com","username":"jjelinek"},"message":"Patch Set 1: Code-Review+1"},{"timestamp":1556752936,"reviewer":{"name":"Patrick Mooney","email":"pmooney@pfmooney.com","username":"pfmooney"},"message":"Patch Set 1: Code-Review+1"},{"timestamp":1556823431,"reviewer":{"name":"Mike Gerdts","email":"mike.gerdts@joyent.com","username":"mgerdts"},"message":"Patch Set 1:\n\nTest notes added to ticket"},{"timestamp":1556824392,"reviewer":{"name":"Jerry Jelinek","email":"jerry.jelinek@joyent.com","username":"jjelinek"},"message":"Patch Set 1: Integration-Approval+1"},{"timestamp":1556825850,"reviewer":{"name":"Mike Gerdts","email":"mike.gerdts@joyent.com","username":"mgerdts"},"message":"Patch Set 2: Patch Set 1 was rebased"},{"timestamp":1556825960,"reviewer":{"name":"Mike Gerdts","email":"mike.gerdts@joyent.com","username":"mgerdts"},"message":"Patch Set 3: Commit message was updated."},{"timestamp":1556826587,"reviewer":{"name":"Gerrit Code Review","email":"no-reply@cr.joyent.us"},"message":"Change has been successfully merged by Mike Gerdts"}],"currentPatchSet":{"number":"3","revision":"38ab7e0ec12be74cc501e210e468de0c3e49c45f","parents":["45d2f6a617bfe6c46ea2f779e3898b5518163af7"],"ref":"refs/changes/86/6186/3","uploader":{"name":"Mike Gerdts","email":"mike.gerdts@joyent.com","username":"mgerdts"},"createdOn":1556825960,"author":{"name":"Mike Gerdts","email":"mike.gerdts@joyent.com","username":"mgerdts"},"isDraft":false,"kind":"NO_CODE_CHANGE","approvals":[{"type":"Code-Review","description":"Code-Review","value":"1","grantedOn":1556749579,"by":{"name":"Jerry Jelinek","email":"jerry.jelinek@joyent.com","username":"jjelinek"}},{"type":"Code-Review","description":"Code-Review","value":"1","grantedOn":1556752936,"by":{"name":"Patrick Mooney","email":"pmooney@pfmooney.com","username":"pfmooney"}},{"type":"Integration-Approval","description":"Integration-Approval","value":"1","grantedOn":1556824392,"by":{"name":"Jerry Jelinek","email":"jerry.jelinek@joyent.com","username":"jjelinek"}},{"type":"SUBM","value":"1","grantedOn":1556826587,"by":{"name":"Mike Gerdts","email":"mike.gerdts@joyent.com","username":"mgerdts"}}],"files":[{"file":"/COMMIT_MSG","type":"ADDED","insertions":10,"deletions":0},{"file":"usr/src/cmd/zoneadmd/zcons.c","type":"MODIFIED","insertions":14,"deletions":-10}],"sizeInsertions":14,"sizeDeletions":-10},"patchSets":[{"number":"1","revision":"906f8ed317b42ef0ffba1b8885df6c62443a6de8","parents":["256b90376a3ab4acdc5f69035941c08d0949f373"],"ref":"refs/changes/86/6186/1","uploader":{"name":"Mike Gerdts","email":"mike.gerdts@joyent.com","username":"mgerdts"},"createdOn":1556749311,"author":{"name":"Mike Gerdts","email":"mike.gerdts@joyent.com","username":"mgerdts"},"isDraft":false,"kind":"REWORK","approvals":[{"type":"Code-Review","description":"Code-Review","value":"1","grantedOn":1556749579,"by":{"name":"Jerry Jelinek","email":"jerry.jelinek@joyent.com","username":"jjelinek"}},{"type":"Integration-Approval","description":"Integration-Approval","value":"1","grantedOn":1556824392,"by":{"name":"Jerry Jelinek","email":"jerry.jelinek@joyent.com","username":"jjelinek"}},{"type":"Code-Review","description":"Code-Review","value":"1","grantedOn":1556752936,"by":{"name":"Patrick Mooney","email":"pmooney@pfmooney.com","username":"pfmooney"}}],"files":[{"file":"/COMMIT_MSG","type":"ADDED","insertions":7,"deletions":0},{"file":"usr/src/cmd/zoneadmd/zcons.c","type":"MODIFIED","insertions":14,"deletions":-10}],"sizeInsertions":14,"sizeDeletions":-10},{"number":"2","revision":"7a6f0019b01b4b71057818e0d04114ea0d24a899","parents":["45d2f6a617bfe6c46ea2f779e3898b5518163af7"],"ref":"refs/changes/86/6186/2","uploader":{"name":"Mike Gerdts","email":"mike.gerdts@joyent.com","username":"mgerdts"},"createdOn":1556825850,"author":{"name":"Mike Gerdts","email":"mike.gerdts@joyent.com","username":"mgerdts"},"isDraft":false,"kind":"TRIVIAL_REBASE","approvals":[{"type":"Code-Review","description":"Code-Review","value":"1","grantedOn":1556749579,"by":{"name":"Jerry Jelinek","email":"jerry.jelinek@joyent.com","username":"jjelinek"}},{"type":"Integration-Approval","description":"Integration-Approval","value":"1","grantedOn":1556824392,"by":{"name":"Jerry Jelinek","email":"jerry.jelinek@joyent.com","username":"jjelinek"}},{"type":"Code-Review","description":"Code-Review","value":"1","grantedOn":1556752936,"by":{"name":"Patrick Mooney","email":"pmooney@pfmooney.com","username":"pfmooney"}}],"files":[{"file":"/COMMIT_MSG","type":"ADDED","insertions":7,"deletions":0},{"file":"usr/src/cmd/zoneadmd/zcons.c","type":"MODIFIED","insertions":14,"deletions":-10}],"sizeInsertions":14,"sizeDeletions":-10},{"number":"3","revision":"38ab7e0ec12be74cc501e210e468de0c3e49c45f","parents":["45d2f6a617bfe6c46ea2f779e3898b5518163af7"],"ref":"refs/changes/86/6186/3","uploader":{"name":"Mike Gerdts","email":"mike.gerdts@joyent.com","username":"mgerdts"},"createdOn":1556825960,"author":{"name":"Mike Gerdts","email":"mike.gerdts@joyent.com","username":"mgerdts"},"isDraft":false,"kind":"NO_CODE_CHANGE","approvals":[{"type":"Code-Review","description":"Code-Review","value":"1","grantedOn":1556749579,"by":{"name":"Jerry Jelinek","email":"jerry.jelinek@joyent.com","username":"jjelinek"}},{"type":"Integration-Approval","description":"Integration-Approval","value":"1","grantedOn":1556824392,"by":{"name":"Jerry Jelinek","email":"jerry.jelinek@joyent.com","username":"jjelinek"}},{"type":"Code-Review","description":"Code-Review","value":"1","grantedOn":1556752936,"by":{"name":"Patrick Mooney","email":"pmooney@pfmooney.com","username":"pfmooney"}},{"type":"SUBM","value":"1","grantedOn":1556826587,"by":{"name":"Mike Gerdts","email":"mike.gerdts@joyent.com","username":"mgerdts"}}],"files":[{"file":"/COMMIT_MSG","type":"ADDED","insertions":10,"deletions":0},{"file":"usr/src/cmd/zoneadmd/zcons.c","type":"MODIFIED","insertions":14,"deletions":-10}],"sizeInsertions":14,"sizeDeletions":-10}],"allReviewers":[{"name":"Jerry Jelinek","email":"jerry.jelinek@joyent.com","username":"jjelinek"},{"name":"Patrick Mooney","email":"pmooney@pfmooney.com","username":"pfmooney"},{"name":"Mike Gerdts","email":"mike.gerdts@joyent.com","username":"mgerdts"}]}